qubitconfig/__init__.py
qubitconfig/envelope_pulse.py
qubitconfig/qchip.py
qubitconfig/utils.py
qubitconfig/wiremap.py
qubitconfig-25.5.1.dist-info/METADATA
qubitconfig-25.5.1.dist-info/WHEEL
qubitconfig-25.5.1.dist-info/licenses/LICENSE
qubitconfig-25.5.1.dist-info/RECORD
