Metadata-Version: 2.4
Name: qubitconfig
Version: 25.5.1
License-File: LICENSE
Requires-Dist: numpy
